stormlibpp/__init__.py
stormlibpp/_args.py
stormlibpp/errors.py
stormlibpp/hfeed.py
stormlibpp/hstorm.py
stormlibpp/httpcore.py
stormlibpp/import.py
stormlibpp/node.py
stormlibpp/output.py
stormlibpp/stormcli.py
stormlibpp/stormpkg.py
stormlibpp/telepath.py
stormlibpp/tmpcortex.py
stormlibpp/utils.py
stormlibpp-0.10.1.dist-info/LICENSE
stormlibpp-0.10.1.dist-info/METADATA
stormlibpp-0.10.1.dist-info/WHEEL
stormlibpp-0.10.1.dist-info/top_level.txt
stormlibpp-0.10.1.dist-info/RECORD
