Metadata-Version: 2.1
Name: stormlibpp
Version: 0.10.1
Summary: The stormlibpp Python package
Author: John Gorman
License: MIT License
Project-URL: Homepage, https://github.com/gormaniac/stormlibpp
Project-URL: Documentation, https://gormo.co/stormlibpp/
Requires-Python: >=3.11
License-File: LICENSE
Requires-Dist: synapse >=2.139.0
